tests/__init__.py
tests/test_frame_colors.py
tests/test_run_video_latency_test.py
tests/test_video_capture_cv2_camera.py
tests/test_video_capture_interface.py
tests/test_video_output_framebuffer.py
tests/test_video_output_interface.py
video_latency_test/__init__.py
video_latency_test/frame_color/__init__.py
video_latency_test/video_capture/__init__.py
video_latency_test/video_capture/cv2_camera.py
video_latency_test/video_capture/interface.py
video_latency_test/video_output/__init__.py
video_latency_test/video_output/framebuffer.py
video_latency_test/video_output/interface.py
video_latency_test-0.0.7.dist-info/LICENSE
video_latency_test-0.0.7.dist-info/METADATA
video_latency_test-0.0.7.dist-info/WHEEL
video_latency_test-0.0.7.dist-info/entry_points.txt
video_latency_test-0.0.7.dist-info/top_level.txt
video_latency_test-0.0.7.dist-info/RECORD
