Metadata-Version: 2.1
Name: video-latency-test
Version: 0.0.7
Summary: A simple test for detecting video latency
Home-page: https://bitbucket.org/pseudodesign/video-latency-test
Author: PseudoDesign
Author-email: info@pseudo.design
License: UNKNOWN
Platform: UNKNOWN
Classifier: Development Status :: 3 - Alpha
Classifier: Intended Audience :: Developers
Classifier: License :: OSI Approved :: MIT License
Classifier: Programming Language :: Python :: 3.6
Classifier: Programming Language :: Python :: 3.7
Classifier: Programming Language :: Python :: 3.8
Classifier: Programming Language :: Python :: 3.9
Requires-Python: >=3.6
Requires-Dist: numpy
Requires-Dist: nptyping
Requires-Dist: func-timeout
Requires-Dist: opencv-python
Provides-Extra: test
Requires-Dist: coverage ; extra == 'test'
Requires-Dist: codecov ; extra == 'test'
Requires-Dist: pyfakefs ; extra == 'test'
